{
    "OA": 80.0,
    "AA": 81.29974160206717,
    "OOD": null,
    "NMI": null,
    "H-score": null,
    "H3-score": null,
    "Recall-all": [
        100.0,
        100.0,
        100.0,
        96.29629629629629,
        59.25925925925925,
        0.0,
        67.44186046511628,
        100.0,
        100.0,
        90.0
    ],
    "Closed Set Accuracy": {
        "OA": 97.28813559322033,
        "AA": 97.59862187769166,
        "Recall-all": [
            100.0,
            100.0,
            100.0,
            96.29629629629629,
            100.0,
            93.33333333333333,
            93.02325581395348,
            100.0,
            100.0,
            93.33333333333333
        ]
    },
    "OSR Accuracy": null
}