{
    "OA": 54.61847389558233,
    "AA": 63.59929925147318,
    "OOD": null,
    "NMI": null,
    "H-score": null,
    "H3-score": null,
    "Recall-all": [
        75.0,
        90.47619047619048,
        75.0,
        92.3076923076923,
        60.0,
        62.5,
        9.090909090909092,
        58.333333333333336,
        100.0,
        13.043478260869565,
        0.0,
        66.66666666666666,
        25.0,
        100.0,
        100.0,
        100.0,
        13.333333333333334,
        37.5,
        0.0,
        70.0,
        100.0,
        100.0,
        100.0,
        50.0,
        100.0,
        100.0,
        100.0,
        3.8461538461538463,
        28.57142857142857,
        40.909090909090914,
        100.0
    ],
    "Closed Set Accuracy": {
        "OA": 99.3975903614458,
        "AA": 99.60711331679072,
        "Recall-all": [
            100.0,
            100.0,
            100.0,
            100.0,
            100.0,
            91.66666666666666,
            100.0,
            100.0,
            100.0,
            100.0,
            100.0,
            100.0,
            100.0,
            100.0,
            100.0,
            100.0,
            100.0,
            100.0,
            100.0,
            100.0,
            100.0,
            100.0,
            100.0,
            100.0,
            100.0,
            100.0,
            100.0,
            96.15384615384616,
            100.0,
            100.0,
            100.0
        ]
    },
    "OSR Accuracy": null
}